MANIFEST.in
README.rst
setup.py
packer/__init__.py
packer/command_line.py
packer/helpers.py
packer/packages.py
packer/packer.py
packer.egg-info/PKG-INFO
packer.egg-info/SOURCES.txt
packer.egg-info/dependency_links.txt
packer.egg-info/entry_points.txt
packer.egg-info/not-zip-safe
packer.egg-info/requires.txt
packer.egg-info/top_level.txt