Metadata-Version: 1.0
Name: packer
Version: 0.1.1
Summary: A new type of package manager
Home-page: http://github.com/kalail/packer
Author: Kashif Malik
Author-email: kashif@kalail.com
License: Copyright (c) 2013 Kashif Malik
